elasticmagic_qf_attrs/__init__.py
elasticmagic_qf_attrs/facet.py
elasticmagic_qf_attrs/facet_result.py
elasticmagic_qf_attrs/simple.py
elasticmagic_qf_attrs/util.py
elasticmagic_qf_attrs-0.1.4.dist-info/WHEEL
elasticmagic_qf_attrs-0.1.4.dist-info/METADATA
elasticmagic_qf_attrs-0.1.4.dist-info/RECORD
